rest_framework_social_oauth2/__init__.py
rest_framework_social_oauth2/authentication.py
rest_framework_social_oauth2/backends.py
rest_framework_social_oauth2/oauth2_backends.py
rest_framework_social_oauth2/oauth2_endpoints.py
rest_framework_social_oauth2/oauth2_grants.py
rest_framework_social_oauth2/settings.py
rest_framework_social_oauth2/urls.py
rest_framework_social_oauth2/views.py
django_rest_framework_social_oauth2-1.2.0.dist-info/LICENSE.txt
django_rest_framework_social_oauth2-1.2.0.dist-info/METADATA
django_rest_framework_social_oauth2-1.2.0.dist-info/WHEEL
django_rest_framework_social_oauth2-1.2.0.dist-info/top_level.txt
django_rest_framework_social_oauth2-1.2.0.dist-info/RECORD
