Metadata-Version: 2.1
Name: django-rest-framework-social-oauth2
Version: 1.2.0
Summary: python-social-auth and oauth2 support for django-rest-framework
Home-page: https://github.com/PhilipGarnero/django-rest-framework-social-oauth2
Author: Philip Garnero
Author-email: philip.garnero@gmail.com
License: MIT
Classifier: Development Status :: 4 - Beta
Classifier: Environment :: Web Environment
Classifier: Framework :: Django
Classifier: License :: OSI Approved :: MIT License
Classifier: Programming Language :: Python :: 3
Classifier: Topic :: Internet :: WWW/HTTP
Classifier: Topic :: Software Development :: Libraries :: Python Modules
License-File: LICENSE.txt
Requires-Dist: djangorestframework>=3.10.3
Requires-Dist: django-oauth-toolkit>=0.12.0
Requires-Dist: social-auth-app-django>=3.1.0
